tests/__init__.py
tests/test_client.py
tests/test_vault_client.py
vault_client/__init__.py
vault_client/client.py
vault_client-0.3.4.dist-info/METADATA
vault_client-0.3.4.dist-info/WHEEL
vault_client-0.3.4.dist-info/top_level.txt
vault_client-0.3.4.dist-info/RECORD
