Metadata-Version: 2.1
Name: vault-client
Version: 0.3.4
Summary: This library implements wrapper for ...
Home-page: https://github.com/Flesspro/vault-client
Author: Sergey Urvanov
Author-email: s.urvanov@gmail.com
License: UNKNOWN
Platform: UNKNOWN
Classifier: Programming Language :: Python :: 3.7
Classifier: Operating System :: OS Independent
Requires-Dist: setuptools (>=49.6.0)
Requires-Dist: loguru (>=0.5.1)
Requires-Dist: certifi (>=2020.6.20)
Requires-Dist: chardet (>=3.0.4)
Requires-Dist: hvac (>=0.10.5)
Requires-Dist: idna (>=2.10)
Requires-Dist: pyhcl (>=0.4.4)
Requires-Dist: requests (>=2.24.0)
Requires-Dist: six (>=1.15.0)
Requires-Dist: urllib3 (>=1.25.10)
Requires-Dist: python-dotenv (>=0.14.0)
